README.md
setup.py
PyQL3/__init__.py
PyQL3/core.py
PyQL3/shell.py
pyql3.egg-info/PKG-INFO
pyql3.egg-info/SOURCES.txt
pyql3.egg-info/dependency_links.txt
pyql3.egg-info/top_level.txt